pydiscourse/__init__.py
pydiscourse/client.py
pydiscourse/exceptions.py
pydiscourse/main.py
pydiscourse/sso.py
pydiscourse-1.6.1.dist-info/AUTHORS
pydiscourse-1.6.1.dist-info/LICENSE
pydiscourse-1.6.1.dist-info/METADATA
pydiscourse-1.6.1.dist-info/WHEEL
pydiscourse-1.6.1.dist-info/entry_points.txt
pydiscourse-1.6.1.dist-info/top_level.txt
pydiscourse-1.6.1.dist-info/RECORD
