Metadata-Version: 2.1
Name: pydiscourse
Version: 1.6.1
Summary: "A Python library for the Discourse API"
Home-page: https://github.com/bennylope/pydiscourse
Author: "Marc Sibson and contributors"
Author-email: "ben@benlopatin.com"
License: "MIT"
Platform: OS Independent
License-File: LICENSE
License-File: AUTHORS
Requires-Dist: requests >=2.4.2
